logic_lang/__init__.py
logic_lang/ast_nodes.py
logic_lang/exceptions.py
logic_lang/interpreter.py
logic_lang/loss.py
logic_lang/parser.py
logic_lang/soft_logic.py
logic_lang-0.2.5.dist-info/licenses/LICENSE
logic_lang-0.2.5.dist-info/METADATA
logic_lang-0.2.5.dist-info/WHEEL
logic_lang-0.2.5.dist-info/top_level.txt
logic_lang-0.2.5.dist-info/RECORD
