Metadata-Version: 2.4
Name: logic-lang
Version: 0.2.5
Summary: A domain-specific language for defining soft logic constraints in medical/general domains
Author-email: Mahbod Issaiy <mahbodissaiy2@gmail.com>
License-Expression: MIT
Project-URL: Homepage, https://github.com/mahbodez/logic-lang-package
Project-URL: Documentation, https://github.com/mahbodez/logic-lang-package#readme
Project-URL: Repository, https://github.com/mahbodez/logic-lang-package.git
Project-URL: Bug Tracker, https://github.com/mahbodez/logic-lang-package/issues
Keywords: logic,constraints,dsl,medical-imaging,soft-logic,rule-based,soft-constraints
Classifier: Development Status :: 4 - Beta
Classifier: Intended Audience :: Developers
Classifier: Intended Audience :: Science/Research
Classifier: Operating System :: OS Independent
Classifier: Programming Language :: Python :: 3
Classifier: Programming Language :: Python :: 3.8
Classifier: Programming Language :: Python :: 3.9
Classifier: Programming Language :: Python :: 3.10
Classifier: Programming Language :: Python :: 3.11
Classifier: Programming Language :: Python :: 3.12
Classifier: Topic :: Scientific/Engineering :: Artificial Intelligence
Classifier: Topic :: Software Development :: Interpreters
Requires-Python: >=3.8
License-File: LICENSE
Requires-Dist: torch>=1.9.0
Requires-Dist: numpy>=1.20.0
Provides-Extra: dev
Requires-Dist: pytest>=6.0; extra == "dev"
Requires-Dist: pytest-cov; extra == "dev"
Requires-Dist: black; extra == "dev"
Requires-Dist: flake8; extra == "dev"
Requires-Dist: mypy; extra == "dev"
Dynamic: license-file
